torchfont/__init__.py
torchfont/_torchfont.abi3.so
torchfont/_torchfont.pyi
torchfont/datasets/__init__.py
torchfont/datasets/folder.py
torchfont/datasets/google_fonts.py
torchfont/datasets/repo.py
torchfont/io/__init__.py
torchfont/io/git.py
torchfont/io/outline.py
torchfont/py.typed
torchfont/transforms/__init__.py
torchfont/transforms/transforms.py
torchfont-0.7.1.dist-info/METADATA
torchfont-0.7.1.dist-info/WHEEL
torchfont-0.7.1.dist-info/licenses/LICENSE
torchfont.libs/libgcc_s-6d2d9dc8.so.1
torchfont-0.7.1.dist-info/RECORD
