Metadata-Version: 2.4
Name: torchfont
Version: 0.7.1
Classifier: Development Status :: 4 - Beta
Classifier: Intended Audience :: Developers
Classifier: Intended Audience :: Science/Research
Classifier: License :: OSI Approved :: MIT License
Classifier: Operating System :: OS Independent
Classifier: Programming Language :: Python :: 3
Classifier: Programming Language :: Python :: 3.10
Classifier: Programming Language :: Python :: 3.11
Classifier: Programming Language :: Python :: 3.12
Classifier: Programming Language :: Python :: 3.13
Classifier: Programming Language :: Python :: Implementation :: CPython
Classifier: Programming Language :: Python :: Implementation :: PyPy
Classifier: Programming Language :: Rust
Classifier: Topic :: Scientific/Engineering :: Artificial Intelligence
Classifier: Topic :: Software Development :: Libraries :: Python Modules
Classifier: Typing :: Typed
Requires-Dist: pygit2>=1.18.2
Requires-Dist: rich>=14.2.0
Requires-Dist: torch>=2.3.0
License-File: LICENSE
Summary: Datasets, Transforms and Models specific to Vector Fonts
Author-email: Takumu Fujioka <fjktkm@gmail.com>
Requires-Python: >=3.10
